MANIFEST.in
README.md
dev_requirements.txt
requirements.txt
setup.cfg
setup.py
versioneer.py
cif_protocol/__init__.py
cif_protocol/_version.py
cif_protocol/constants.py
cif_protocol/msg.py
cif_protocol.egg-info/PKG-INFO
cif_protocol.egg-info/SOURCES.txt
cif_protocol.egg-info/dependency_links.txt
cif_protocol.egg-info/requires.txt
cif_protocol.egg-info/top_level.txt