Metadata-Version: 1.1
Name: cif-protocol
Version: 0.0.0a1
Summary: CIF Protocol
Home-page: https://github.com/csirtgadgets/cif-protocol-py
Author: Wes Young
Author-email: wes@csirtgadgets.org
License: MPLv2
Keywords: security
Platform: UNKNOWN
Classifier: Topic :: System :: Networking
Classifier: Environment :: Other Environment
Classifier: Intended Audience :: Developers
Classifier: Programming Language :: Python
